LICENSE
MANIFEST.in
README.rst
requirements.txt
setup.py
django_excalibur/__init__.py
django_excalibur/admin.py
django_excalibur/decorators.py
django_excalibur/exceptions.py
django_excalibur/middleware.py
django_excalibur/models.py
django_excalibur/utils.py
django_excalibur.egg-info/PKG-INFO
django_excalibur.egg-info/SOURCES.txt
django_excalibur.egg-info/dependency_links.txt
django_excalibur.egg-info/pbr.json
django_excalibur.egg-info/requires.txt
django_excalibur.egg-info/top_level.txt
django_excalibur/tests/__init__.py
django_excalibur/tests/rundjango.py
django_excalibur/tests/test_excalibur.py
django_excalibur/tests/plugins/Apogee.py
django_excalibur/tests/plugins/Bnu.py
django_excalibur/tests/plugins/Harpege.py
django_excalibur/tests/plugins/Ldapuds.py
django_excalibur/tests/plugins/__init__.py