Metadata-Version: 1.1
Name: django-excalibur
Version: 0.0.3
Summary: Django Rest Framework implementation for Excalibur : A tool to manage plugins
Home-page: https://github.com/unistra/django-excalibur
Author: Morgan Bohn
Author-email: morgan.bohn@unistra.fr
License: UNKNOWN
Download-URL: https://github.com/unistra/django-excalibur
Keywords: django,excalibur,plugins
Platform: UNKNOWN
Classifier: Development Status :: 3 - Alpha
Classifier: Environment :: Web Environment
Classifier: Framework :: Django
Classifier: Intended Audience :: Developers
Classifier: License :: OSI Approved :: GNU General Public License v2 (GPLv2)
Classifier: Programming Language :: Python :: 2.7
Classifier: Programming Language :: Python :: 3
